mimedetector/__init__.py
mimedetector/core.py
mimedetector-0.2.1.dist-info/METADATA
mimedetector-0.2.1.dist-info/WHEEL
mimedetector-0.2.1.dist-info/licenses/LICENSE
mimedetector-0.2.1.dist-info/RECORD
