Metadata-Version: 2.4
Name: mimedetector
Version: 0.2.1
Summary: A Python package for detecting MIME types of local files and URLs
Project-URL: Homepage, https://github.com/woopygit/mimedetector
Project-URL: Bug Tracker, https://github.com/woopygit/mimedetector/issues
Author-email: woopygit <woopygit@icloud.com>
License-File: LICENSE
Classifier: License :: OSI Approved :: MIT License
Classifier: Operating System :: OS Independent
Classifier: Programming Language :: Python :: 3
Classifier: Programming Language :: Python :: 3.7
Classifier: Programming Language :: Python :: 3.8
Classifier: Programming Language :: Python :: 3.9
Classifier: Programming Language :: Python :: 3.10
Classifier: Programming Language :: Python :: 3.11
Requires-Python: >=3.7
Requires-Dist: requests>=2.25.1
